routing/__init__.py
routing/app_settings.py
routing/apps.py
routing/edges.py
routing/graph.py
routing/models.py
routing/routing.py
routing/static_data.py
routing/tasks.py
routing/trigInvasionSystems.csv
routing/locale/en/LC_MESSAGES/django.mo
routing/locale/en/LC_MESSAGES/django.po
routing/management/commands/routing_precompute.py
routing/migrations/0001_initial.py
routing/migrations/0002_solarsystemconnection_prefer_less_safe_and_more.py
routing/migrations/0003_triginvasion.py
routing/migrations/0004_rename_prefer_less_safe_solarsystemconnection_p_less_safe_and_more.py
routing/migrations/0005_rename_security_status_solarsystem_security.py
routing/migrations/__init__.py
routing/tests/__init__.py
routing/tests/test_models.py
routing/tests/test_routing.py
aa_routing-0.3.0a0.dist-info/licenses/LICENSE
aa_routing-0.3.0a0.dist-info/WHEEL
aa_routing-0.3.0a0.dist-info/METADATA
aa_routing-0.3.0a0.dist-info/RECORD
